pathops/__init__.py
pathops/_pathops.pypy311-pp73-aarch64-linux-gnu.so
pathops/_version.py
pathops/operations.py
skia_pathops-0.9.1.dist-info/METADATA
skia_pathops-0.9.1.dist-info/WHEEL
skia_pathops-0.9.1.dist-info/top_level.txt
skia_pathops-0.9.1.dist-info/RECORD
skia_pathops-0.9.1.dist-info/licenses/LICENSE
