Metadata-Version: 2.4
Name: skia-pathops
Version: 0.9.1
Summary: Python access to operations on paths using the Skia library
Home-page: https://github.com/fonttools/skia-pathops
Author: Khaled Hosny, Cosimo Lupo
Author-email: fonttools@googlegroups.com
License: BSD-3-Clause
Classifier: Development Status :: 4 - Beta
Classifier: Environment :: Console
Classifier: Intended Audience :: Developers
Classifier: License :: OSI Approved :: BSD License
Classifier: Operating System :: OS Independent
Classifier: Programming Language :: Python
Classifier: Programming Language :: Python :: 3
Classifier: Topic :: Multimedia :: Graphics
Classifier: Topic :: Multimedia :: Graphics :: Graphics Conversion
Requires-Python: >=3.10
License-File: LICENSE
Provides-Extra: testing
Requires-Dist: pytest; extra == "testing"
Requires-Dist: coverage; extra == "testing"
Requires-Dist: pytest-xdist; extra == "testing"
Requires-Dist: pytest-randomly; extra == "testing"
Dynamic: author
Dynamic: author-email
Dynamic: classifier
Dynamic: description
Dynamic: description-content-type
Dynamic: home-page
Dynamic: license
Dynamic: license-file
Dynamic: provides-extra
Dynamic: requires-python
Dynamic: summary
